djpress/__init__.py
djpress/admin.py
djpress/app_settings.py
djpress/apps.py
djpress/checks.py
djpress/conf.py
djpress/exceptions.py
djpress/feeds.py
djpress/markdown_renderer.py
djpress/permissions.py
djpress/signals.py
djpress/sitemaps.py
djpress/url_converters.py
djpress/url_utils.py
djpress/urls.py
djpress/utils.py
djpress/views.py
djpress/management/__init__.py
djpress/management/commands/__init__.py
djpress/management/commands/djpress_export.py
djpress/management/commands/djpress_setup_groups.py
djpress/migrations/0001_initial.py
djpress/migrations/0002_rename_content_type_post_post_type.py
djpress/migrations/0003_post_menu_order.py
djpress/migrations/0004_rename_name_category_title_category_menu_order.py
djpress/migrations/0005_post_parent.py
djpress/migrations/0006_alter_post_parent.py
djpress/migrations/0007_pluginstorage.py
djpress/migrations/0008_alter_post_options_alter_post_managers_and_more.py
djpress/migrations/0009_alter_post_options.py
djpress/migrations/0010_tag_post_tags.py
djpress/migrations/0011_media.py
djpress/migrations/0012_alter_post_title.py
djpress/migrations/0013_alter_post_slug_alter_post_title.py
djpress/migrations/0014_rename_date_post_published_at_and_more.py
djpress/migrations/0015_alter_media_options_and_more.py
djpress/migrations/0016_post__date.py
djpress/migrations/0017_populate_post__date_field.py
djpress/migrations/0018_post_djpress_post_title_idx_and_more.py
djpress/migrations/__init__.py
djpress/models/__init__.py
djpress/models/category.py
djpress/models/media.py
djpress/models/plugin_storage.py
djpress/models/post.py
djpress/models/tag.py
djpress/plugins/__init__.py
djpress/plugins/base_plugin.py
djpress/plugins/handlers.py
djpress/plugins/hook_registry.py
djpress/plugins/plugin_registry.py
djpress/plugins/protocols.py
djpress/static/default/css/style.css
djpress/static/simple/css/simple.min.css
djpress/static/simple/css/style.css
djpress/templates/djpress/default/index.html
djpress/templates/djpress/simple/index.html
djpress-0.22.3.dist-info/METADATA
djpress-0.22.3.dist-info/WHEEL
djpress-0.22.3.dist-info/licenses/LICENSE
djpress-0.22.3.dist-info/RECORD
