Metadata-Version: 2.4
Name: djpress
Version: 0.22.3
Summary: A blog application for Django sites, inspired by classic WordPress.
Project-URL: Homepage, https://github.com/stuartmaxwell/djpress
Project-URL: Documentation, https://stuartmaxwell.github.io/djpress/
Project-URL: Repository, https://github.com/stuartmaxwell/djpress
Project-URL: Issues, https://github.com/stuartmaxwell/djpress/issues
Author-email: Stuart Maxwell <stuart@amanzi.nz>
License: MIT License
License-File: LICENSE
Keywords: blog,cms,django,markdown,wordpress
Classifier: Development Status :: 3 - Alpha
Classifier: Environment :: Web Environment
Classifier: Framework :: Django
Classifier: Framework :: Django :: 4.2
Classifier: Framework :: Django :: 5.0
Classifier: Framework :: Django :: 5.1
Classifier: Framework :: Django :: 5.2
Classifier: Framework :: Django :: 6.0
Classifier: Intended Audience :: Developers
Classifier: License :: OSI Approved :: MIT License
Classifier: Operating System :: OS Independent
Classifier: Programming Language :: Python
Classifier: Programming Language :: Python :: 3
Classifier: Programming Language :: Python :: 3 :: Only
Classifier: Programming Language :: Python :: 3.10
Classifier: Programming Language :: Python :: 3.11
Classifier: Programming Language :: Python :: 3.12
Classifier: Programming Language :: Python :: 3.13
Classifier: Programming Language :: Python :: 3.14
Classifier: Topic :: Internet :: WWW/HTTP
Classifier: Topic :: Internet :: WWW/HTTP :: Dynamic Content
Requires-Python: >=3.10
Requires-Dist: django<6.1,>=4.2.0
Requires-Dist: markdown>=3.7
Provides-Extra: docs
Requires-Dist: cogapp>=3.4.1; extra == 'docs'
Requires-Dist: furo>=2024.8.6; extra == 'docs'
Requires-Dist: myst-parser>=4.0.0; extra == 'docs'
Requires-Dist: sphinx-autobuild>=2024.10.3; extra == 'docs'
Requires-Dist: sphinx-copybutton>=0.5.2; extra == 'docs'
Requires-Dist: sphinx-rtd-theme>=3.0.1; extra == 'docs'
Requires-Dist: sphinx>=8.1.3; extra == 'docs'
Provides-Extra: test
Requires-Dist: django-debug-toolbar>=4.4.0; extra == 'test'
Requires-Dist: djpress-example-plugin; extra == 'test'
Requires-Dist: nox>=2024.4.15; extra == 'test'
Requires-Dist: pytest-cov>=6.0.0; extra == 'test'
Requires-Dist: pytest-coverage>=0.0; extra == 'test'
Requires-Dist: pytest-django>=4.9.0; extra == 'test'
Requires-Dist: pytest>=8.3.3; extra == 'test'
Requires-Dist: rich>=14.2.0; extra == 'test'
